linalgebralib/LinAlgebraLib.py
linalgebralib/__init__.py
linalgebralib-0.0.31.dist-info/METADATA
linalgebralib-0.0.31.dist-info/WHEEL
linalgebralib-0.0.31.dist-info/licenses/LICENSE
linalgebralib-0.0.31.dist-info/RECORD
