Metadata-Version: 2.3
Name: linalgebralib
Version: 0.0.31
Summary: This package contains a library of methods and classes relating to Linear Algebra.
Project-URL: Homepage, https://github.com/aauthur/LinAlgebraLib
Author-email: Adam Authur <aauthur@tamu.edu>
License-File: LICENSE
Classifier: License :: OSI Approved :: MIT License
Classifier: Operating System :: OS Independent
Classifier: Programming Language :: Python :: 3
Requires-Python: >=3.9
